LICENSE.txt
MANIFEST.in
README.md
TODO
mypy.ini
pyproject.toml
tox.ini
src/simplegtd/__init__.py
src/simplegtd/filterlist.py
src/simplegtd/mainwindow.py
src/simplegtd/task.py
src/simplegtd/todotxt.py
src/simplegtd/views.py
src/simplegtd.egg-info/PKG-INFO
src/simplegtd.egg-info/SOURCES.txt
src/simplegtd.egg-info/dependency_links.txt
src/simplegtd.egg-info/entry_points.txt
src/simplegtd.egg-info/requires.txt
src/simplegtd.egg-info/top_level.txt
src/simplegtd/data/applications/simplegtd.desktop
src/simplegtd/data/icons/simplegtd.svg
src/simplegtd/data/ui/shortcuts-window.ui
src/simplegtd/libwhiz/__init__.py
src/simplegtd/libwhiz/css.py
src/simplegtd/libwhiz/path.py
src/simplegtd/libwhiz/rememberingwindow.py
src/simplegtd/models/__init__.py
src/simplegtd/models/blobstore.py
src/simplegtd/models/linestore.py
src/simplegtd/models/liststoresyncer.py
src/simplegtd/models/taskstore.py
src/simplegtd/models/test_linestore.py
src/simplegtd/models/test_taskstore.py
src/simplegtd/models/fixtures/after.txt
src/simplegtd/models/fixtures/before.txt