Metadata-Version: 2.2
Name: simplegtd
Version: 0.0.26
Summary: Manage your todo.txt task list using the Getting Things Done system.
Author-email: "Manuel Amador (Rudd-O)" <rudd-o@rudd-o.com>
License:                     GNU GENERAL PUBLIC LICENSE
Project-URL: Homepage, https://github.com/Rudd-O/simplegtd
Project-URL: Repository, https://github.com/Rudd-O/simplegtd
Project-URL: Issues, https://github.com/Rudd-O/simplegtd/issues
Keywords: gtd,getting things done,TODO.TXT
Classifier: Development Status :: 3 - Alpha
Classifier: Environment :: X11 Applications :: GTK
Classifier: Intended Audience :: End Users/Desktop
Classifier: License :: OSI Approved :: GNU General Public License v3 or later (GPLv3+)
Classifier: Operating System :: POSIX :: Linux
Classifier: Programming Language :: Python :: 3 :: Only
Classifier: Topic :: Office/Business :: Scheduling
Classifier: Topic :: Office/Business :: Groupware
License-File: LICENSE.txt
Requires-Dist: pyxdg
